dwave/__init__.py
dwave/plugins/__init__.py
dwave/plugins/torch/__init__.py
dwave/plugins/torch/utils.py
dwave/plugins/torch/models/__init__.py
dwave/plugins/torch/models/boltzmann_machine.py
dwave/plugins/torch/models/discrete_variational_autoencoder.py
dwave/plugins/torch/models/losses/__init__.py
dwave/plugins/torch/models/losses/kl_divergence.py
dwave_pytorch_plugin-0.2.0.dist-info/licenses/LICENSE
examples/boltzmann_machine.py
tests/test_boltzmann_machine.py
tests/test_dvae_winci2020.py
tests/test_utils.py
dwave_pytorch_plugin-0.2.0.dist-info/METADATA
dwave_pytorch_plugin-0.2.0.dist-info/WHEEL
dwave_pytorch_plugin-0.2.0.dist-info/top_level.txt
dwave_pytorch_plugin-0.2.0.dist-info/RECORD
