Metadata-Version: 2.4
Name: dwave-pytorch-plugin
Version: 0.2.0
Summary: PyTorch plugin.
Author-email: "D-Wave Inc." <tools@dwavesys.com>
License:                                  Apache License
Project-URL: Homepage, https://github.com/dwavesystems/dwave-pytorch-plugin
Project-URL: Download, https://github.com/dwavesystems/dwave-pytorch-plugin/releases
Classifier: Operating System :: Microsoft :: Windows
Classifier: Operating System :: POSIX
Classifier: Operating System :: Unix
Classifier: Operating System :: MacOS
Classifier: Programming Language :: Python
Classifier: Programming Language :: Python :: 3
Classifier: Programming Language :: Python :: 3.9
Classifier: Programming Language :: Python :: 3.10
Classifier: Programming Language :: Python :: 3.11
Classifier: Programming Language :: Python :: 3.12
Classifier: Programming Language :: Python :: 3.13
Classifier: Programming Language :: Python :: 3 :: Only
Requires-Python: >=3.9
License-File: LICENSE
Requires-Dist: numpy>=1.24.4
Requires-Dist: torch
Requires-Dist: networkx
Requires-Dist: dimod
Requires-Dist: dwave-system
Requires-Dist: dwave-hybrid
Dynamic: license-file
